iftttcml/__init__.py
iftttcml/buildparser.py
iftttcml/iftttcml.py
iftttcml/iftttmakerevent.py
iftttcml/events/__init__.py
iftttcml/events/metrovlc_sin_saldo.py
iftttcml/events/people_in_space.py
iftttcml/events/template.py
iftttcml-0.5.1.dist-info/DESCRIPTION.rst
iftttcml-0.5.1.dist-info/METADATA
iftttcml-0.5.1.dist-info/RECORD
iftttcml-0.5.1.dist-info/WHEEL
iftttcml-0.5.1.dist-info/entry_points.txt
iftttcml-0.5.1.dist-info/metadata.json
iftttcml-0.5.1.dist-info/top_level.txt
