Metadata-Version: 2.0
Name: iftttcml
Version: 0.5.1
Summary: ITFFF: custom maker launcher
Home-page: https://bitbucket.com/penicolas/ifttt-cml
Author: penicolas
Author-email: png1981@gmail.com
License: UNKNOWN
Platform: UNKNOWN
Classifier: Programming Language :: Python
Classifier: Development Status :: 3 - Alpha
Classifier: License :: OSI Approved :: MIT License
Classifier: Operating System :: OS Independent
Classifier: Programming Language :: Python :: 3 :: Only
Classifier: Topic :: Utilities
Requires-Dist: metrovlc
